Metadata-Version: 2.1
Name: django-99minutos
Version: 1.0.0
Summary: Django 99minutos Integration
Home-page: https://gitlab.com/linets/ecommerce/oms/integrations/django-99minutos/
Author: Linets Development Team
Author-email: dteam@linets.cl
License: MIT
Platform: UNKNOWN
Requires-Python: >=3.7
